montelo/Montelo.py
montelo/MonteloClient.py
montelo/__init__.py
montelo/client/.openapi-generator/FILES
montelo/client/.openapi-generator/VERSION
montelo/client/.openapi-generator-ignore
montelo/client/openapi_client/__init__.py
montelo/client/openapi_client/api/__init__.py
montelo/client/openapi_client/api/api_key_api.py
montelo/client/openapi_client/api/datapoint_api.py
montelo/client/openapi_client/api/datapoint_run_api.py
montelo/client/openapi_client/api/dataset_api.py
montelo/client/openapi_client/api/default_api.py
montelo/client/openapi_client/api/environment_api.py
montelo/client/openapi_client/api/experiment_api.py
montelo/client/openapi_client/api/fine_tuning_api.py
montelo/client/openapi_client/api/generate_api.py
montelo/client/openapi_client/api/health_api.py
montelo/client/openapi_client/api/inference_api.py
montelo/client/openapi_client/api/organization_api.py
montelo/client/openapi_client/api/payment_api.py
montelo/client/openapi_client/api/project_api.py
montelo/client/openapi_client/api_client.py
montelo/client/openapi_client/api_response.py
montelo/client/openapi_client/configuration.py
montelo/client/openapi_client/docs/AddToDatasetInput.md
montelo/client/openapi_client/docs/ApiKeyApi.md
montelo/client/openapi_client/docs/ApiKeyWithEnvDto.md
montelo/client/openapi_client/docs/BatchAddToDatasetInput.md
montelo/client/openapi_client/docs/ChatCompletionDto.md
montelo/client/openapi_client/docs/ChoiceDto.md
montelo/client/openapi_client/docs/Config.md
montelo/client/openapi_client/docs/CreateDatapointRunInput.md
montelo/client/openapi_client/docs/CreateDatasetInput.md
montelo/client/openapi_client/docs/CreateEnvInput.md
montelo/client/openapi_client/docs/CreateExperimentInput.md
montelo/client/openapi_client/docs/CreateFineTuneInput.md
montelo/client/openapi_client/docs/CreateProjectInput.md
montelo/client/openapi_client/docs/DatapointApi.md
montelo/client/openapi_client/docs/DatapointDto.md
montelo/client/openapi_client/docs/DatapointRunApi.md
montelo-0.1.4.dist-info/METADATA
montelo-0.1.4.dist-info/WHEEL
montelo-0.1.4.dist-info/RECORD
